Metadata-Version: 1.1
Name: tscomparator
Version: 1.0.3
Summary: A timeseries comparison and analysis tool for Python
Home-page: https://github.com/gellison321/tscomparator
Author: Grant Ellison
Author-email: gellison321@gmail.com
License: UNKNOWN
Download-URL: https://github.com/gellison321/tscomparator/archive/refs/tags/1.0.3.tar.gz
Keywords: timeseries,data science,data analysis,time series comparison
Platform: UNKNOWN
Classifier: Development Status :: 4 - Beta
Classifier: Intended Audience :: Developers
Classifier: Intended Audience :: Science/Research
Classifier: Topic :: Software Development :: Build Tools
Classifier: Operating System :: OS Independent
Classifier: License :: OSI Approved :: MIT License
Classifier: Programming Language :: Python
